setup.py
neuronunit/__init__.py
neuronunit/aibs.py
neuronunit/neuroelectro.py
neuronunit/plottools.py
neuronunit.egg-info/PKG-INFO
neuronunit.egg-info/SOURCES.txt
neuronunit.egg-info/dependency_links.txt
neuronunit.egg-info/requires.txt
neuronunit.egg-info/top_level.txt
neuronunit/capabilities/__init__.py
neuronunit/capabilities/channel.py
neuronunit/capabilities/spike_functions.py
neuronunit/models/__init__.py
neuronunit/models/channel.py
neuronunit/models/reduced.py
neuronunit/neuroconstruct/__init__.py
neuronunit/neuroconstruct/capabilities.py
neuronunit/neuroconstruct/models.py
neuronunit/neuron/__init__.py
neuronunit/neuron/capabilities.py
neuronunit/neuron/models.py
neuronunit/tests/__init__.py
neuronunit/tests/channel.py
neuronunit/tests/dynamics.py