Metadata-Version: 1.0
Name: neuronunit
Version: 0.1.8.2
Summary: A SciUnit library for data-driven testing of single-neuron physiology models.
Home-page: http://github.com/scidash/neuronunit
Author: Rick Gerkin
Author-email: rgerkin@asu.edu
License: MIT
Platform: UNKNOWN
